simple_async_mq/__init__.py
simple_async_mq/client_app.py
simple_async_mq/client_app_example.py
simple_async_mq/client_pub_app_example.py
simple_async_mq/client_sub_app_example.py
simple_async_mq-0.2.5.dist-info/LICENSE.txt
simple_async_mq-0.2.5.dist-info/METADATA
simple_async_mq-0.2.5.dist-info/WHEEL
simple_async_mq-0.2.5.dist-info/top_level.txt
simple_async_mq-0.2.5.dist-info/RECORD
