Metadata-Version: 2.1
Name: simple-async-mq
Version: 0.2.5
Summary: A simple async message queue client - socket-io wrapper
Home-page: https://github.com/3520kramer/simple-async-mq
Author: Oliver Kramer
Author-email: 3520.kramer@gmail.com
License: MIT
Download-URL: https://github.com/3520kramer/simple-async-mq/archive/v_024.tar.gz
Keywords: mq,async,client
Platform: UNKNOWN
Classifier: Development Status :: 3 - Alpha
Classifier: Intended Audience :: Developers
Classifier: Topic :: Software Development :: Build Tools
Classifier: License :: OSI Approved :: MIT License
Classifier: Programming Language :: Python :: 3.9
License-File: LICENSE.txt
Requires-Dist: asyncio
Requires-Dist: python-socketio
Requires-Dist: aiohttp
